archetypeai/__init__.py
archetypeai/_base.py
archetypeai/_capabilities.py
archetypeai/_common.py
archetypeai/_data_processing.py
archetypeai/_errors.py
archetypeai/_files.py
archetypeai/_kafka_client.py
archetypeai/_lens.py
archetypeai/_lens_session_socket.py
archetypeai/_messaging.py
archetypeai/_sensors.py
archetypeai/_socket_manager.py
archetypeai/_sse.py
archetypeai/api_client.py
archetypeai/utils.py
archetypeai-25.12.17.6.dist-info/licenses/LICENSE
archetypeai-25.12.17.6.dist-info/METADATA
archetypeai-25.12.17.6.dist-info/WHEEL
archetypeai-25.12.17.6.dist-info/top_level.txt
archetypeai-25.12.17.6.dist-info/RECORD
