Metadata-Version: 2.4
Name: archetypeai
Version: 25.12.17.6
Summary: The official python client for the Archetype AI API.
Home-page: https://github.com/archetypeai/python-client
Author: Archetype AI
Requires-Python: >=3.8
License-File: LICENSE
Requires-Dist: wheel
Requires-Dist: argparse>=1.4.0
Requires-Dist: typing-extensions>=4.8.0
Requires-Dist: requests>=2.31.0
Requires-Dist: requests-toolbelt>=1.0.0
Requires-Dist: websockets>=12.0
Requires-Dist: websocket-client>=1.8.0
Requires-Dist: kafka-python==2.0.4
Requires-Dist: httpx==0.28.1
Requires-Dist: httpx-sse==0.4.1
Requires-Dist: pyyaml==6.0.2
Requires-Dist: pytest==9.0.1
Dynamic: author
Dynamic: home-page
Dynamic: license-file
Dynamic: requires-dist
Dynamic: requires-python
Dynamic: summary
